Metadata-Version: 2.1
Name: animaty
Version: 0.1
Summary: animaty is a library for animating ascii art in python.
Home-page: https://github.com/GaiaHacking
Author: Vincent Elias Mallon
License: MIT
Download-URL: https://github.com/GaiaHacking/animaty/archive/0.1.tar.gz
Keywords: ASCII,Animation,Console,Terminal
Platform: UNKNOWN
